<icecast>
    <location>Ghana</location>
    <admin>admin@localhost</admin>
    <hostname>localhost</hostname>
    <limits>
        <clients>100</clients>
        <sources>100</sources>
        <queue-size>524288</queue-size>
        <client-timeout>30</client-timeout>
        <header-timeout>15</header-timeout>
        <source-timeout>10</source-timeout>
        <burst-on-connect>1</burst-on-connect>
        <burst-size>65536</burst-size>
    </limits>
    <authentication>
        <source-password>hackme</source-password>
        <relay-password>hackme</relay-password>
        <admin-user>admin</admin-user>
        <admin-password>hackme</admin-password>
    </authentication>
    <listen-socket>
        <port>8000</port>
    </listen-socket>

    <mount type="normal">
        <mount-name>/w00.mp3</mount-name>
        <username>source</username>
        <password>hackme</password>
        <max-listeners>100</max-listeners>
        <max-listener-duration>3600</max-listener-duration>
        <dump-file>/tmp/dump-example1.ogg</dump-file>
        <intro>/open.mp3</intro>
        <fallback-mount>/open.mp3</fallback-mount>
        <fallback-override>1</fallback-override>
        <fallback-when-full>1</fallback-when-full>
        <charset>ISO8859-1</charset>
        <public>1</public>
        <stream-name>My audio stream</stream-name>
        <stream-description>My audio description</stream-description>
        <stream-url>http://some.place.com</stream-url>
        <genre>classical</genre>
        <bitrate>64</bitrate>
        <type>application/mp3</type>
        <subtype>vorbis</subtype>
        <hidden>1</hidden>
        <burst-size>65536</burst-size>
        <mp3-metadata-interval>4096</mp3-metadata-interval>
        <authentication type="xxxxxx">
            <!-- See listener authentiaction documentation -->
        </authentication>
        <http-headers>
            <header name="Access-Control-Allow-Origin" value="*" />
            <header name="X-Robots-Tag" value="index, noarchive" />
            <header name="foo" value="bar" status="200" />
            <header name="Nelson" value="Ha-Ha!" status="404" />
        </http-headers>
        <on-connect>/home/icecast/bin/source-start</on-connect>
        <on-disconnect>/home/icecast/bin/source-end</on-disconnect>
    </mount>

    <http-headers>
        <header name="Access-Control-Allow-Origin" value="*" />
    </http-headers>
    <fileserve>1</fileserve>
    <paths>
        <logdir>./log</logdir>
        <webroot>./web</webroot>
        <adminroot>./admin</adminroot>
        <alias source="/" destination="/status.xsl"/>
    </paths>
    <logging>
        <accesslog>access.log</accesslog>
        <errorlog>error.log</errorlog>
        <loglevel>3</loglevel>
        <logsize>10000</logsize>
    </logging>
</icecast>